my_stocks/__init__.py
my_stocks/main.py
my_stocks-0.1.3.dist-info/entry_points.txt
my_stocks-0.1.3.dist-info/WHEEL
my_stocks-0.1.3.dist-info/METADATA
my_stocks-0.1.3.dist-info/RECORD
